LICENSE
MANIFEST.in
Makefile
README.rst
setup.py
datafilters/__init__.py
datafilters/declarative.py
datafilters/decorators.py
datafilters/extra_lookup.py
datafilters/filterform.py
datafilters/filterspec.py
datafilters/models.py
datafilters/views.py
datafilters.egg-info/PKG-INFO
datafilters.egg-info/SOURCES.txt
datafilters.egg-info/dependency_links.txt
datafilters.egg-info/requires.txt
datafilters.egg-info/top_level.txt
datafilters/locale/ru/LC_MESSAGES/django.mo
datafilters/locale/ru/LC_MESSAGES/django.po
datafilters/specs/__init__.py
datafilters/specs/builtin.py
datafilters/specs/extra.py
datafilters/tests/__init__.py
datafilters/tests/specs_builtin.py
sample_proj/__init__.py
sample_proj/manage.py
sample_proj/settings.py
sample_proj/urls.py
sample_proj/polls/__init__.py
sample_proj/polls/filters.py
sample_proj/polls/models.py
sample_proj/polls/tests.py
sample_proj/polls/views.py
sample_proj/polls/fixtures/initial_data.json
sample_proj/polls/templates/base.html
sample_proj/polls/templates/polls/poll_list.html