Metadata-Version: 1.1
Name: datafilters
Version: 0.3.3
Summary: Neat QuerySet filter for django apps with filterforms based on django forms
Home-page: https://github.com/freevoid/django-datafilters
Author: Nikolay Zakharov
Author-email: nikolay@desh.su
License: MIT
Keywords: django filter datafilter queryset
Platform: UNKNOWN
Classifier: Development Status :: 4 - Beta
Classifier: Intended Audience :: Developers
Classifier: Framework :: Django
Classifier: License :: OSI Approved :: MIT License
Classifier: Operating System :: OS Independent
Classifier: Programming Language :: Python
